[
  {
    "uuid": "e41c3129-ef59-4e76-9b7e-524b5a7588c9",
    "name": "Sanesitothenoob",
    "level": 4,
    "bypassesPlayerLimit": false
  },
  {
    "uuid": "5fb3dd41-db04-42bc-b6c9-07cb7f0eafe7",
    "name": "El_Angelardo",
    "level": 4,
    "bypassesPlayerLimit": false
  },
  {
    "uuid": "97b827e4-b140-4aea-8f10-b6633b0e63ce",
    "name": "Tortuga0015yt",
    "level": 4,
    "bypassesPlayerLimit": false
  },
  {
    "uuid": "834c5ff3-40cb-302a-9e7a-9c613a1104ae",
    "name": "Sanesitothenoob",
    "level": 4,
    "bypassesPlayerLimit": false
  }
]